js/.DS_Store
js/README.md
js/package.json
js/webpack.config.js
js/yarn.lock
js/dist/index.js
js/dist/index.js.LICENSE.txt
js/lib/embed.js
js/lib/example.js
js/lib/extension.js
js/lib/index.js
js/lib/labplugin.js
js/lib/widget.js
thomas/jupyter/__build__
thomas/jupyter/__init__.py
thomas/jupyter/_version.py
thomas/jupyter/example.py
thomas/jupyter/widget.py
thomas/jupyter/labextension/package.json
thomas/jupyter/labextension/static/185.2af8e8ef8e36a51d2366.js
thomas/jupyter/labextension/static/261.ecf56d962bc4f733dfab.js
thomas/jupyter/labextension/static/486.f71fc7f2a9dc4c0aad6b.js
thomas/jupyter/labextension/static/486.f71fc7f2a9dc4c0aad6b.js.LICENSE.txt
thomas/jupyter/labextension/static/568.74e31c7583278a33a215.js
thomas/jupyter/labextension/static/614.0f83beaefff9c2379c3f.js
thomas/jupyter/labextension/static/remoteEntry.b81c5aa03be25ff17ce2.js
thomas/jupyter/labextension/static/style.js
thomas/jupyter/nbextension/extension.js
thomas/jupyter/nbextension/index.js
thomas/jupyter/nbextension/index.js.LICENSE.txt
thomas_jupyter_widget-0.1.2.data/data/etc/jupyter/nbconfig/notebook.d/thomas-jupyter-widget.json
thomas_jupyter_widget-0.1.2.data/data/share/jupyter/labextensions/thomas-jupyter-widget/install.json
thomas_jupyter_widget-0.1.2.data/data/share/jupyter/labextensions/thomas-jupyter-widget/package.json
thomas_jupyter_widget-0.1.2.data/data/share/jupyter/labextensions/thomas-jupyter-widget/static/185.2af8e8ef8e36a51d2366.js
thomas_jupyter_widget-0.1.2.data/data/share/jupyter/labextensions/thomas-jupyter-widget/static/261.ecf56d962bc4f733dfab.js
thomas_jupyter_widget-0.1.2.data/data/share/jupyter/labextensions/thomas-jupyter-widget/static/486.f71fc7f2a9dc4c0aad6b.js
thomas_jupyter_widget-0.1.2.data/data/share/jupyter/labextensions/thomas-jupyter-widget/static/486.f71fc7f2a9dc4c0aad6b.js.LICENSE.txt
thomas_jupyter_widget-0.1.2.data/data/share/jupyter/labextensions/thomas-jupyter-widget/static/568.74e31c7583278a33a215.js
thomas_jupyter_widget-0.1.2.dist-info/METADATA
thomas_jupyter_widget-0.1.2.dist-info/WHEEL
thomas_jupyter_widget-0.1.2.dist-info/top_level.txt
thomas_jupyter_widget-0.1.2.dist-info/RECORD
