Metadata-Version: 2.1
Name: thomas-jupyter-widget
Version: 0.1.2
Summary: Widget to display and interact with Bayesian Networks in JupyterLab.
Home-page: https://github.com//thomas-jupyter-widget
Author: Melle Sieswerda
Author-email: m.sieswerda@iknl.nl
License: UNKNOWN
Keywords: ipython,jupyter,widgets
Platform: UNKNOWN
Classifier: Development Status :: 4 - Beta
Classifier: Framework :: IPython
Classifier: Intended Audience :: Developers
Classifier: Intended Audience :: Science/Research
Classifier: Topic :: Multimedia :: Graphics
Classifier: Programming Language :: Python :: 3.6
Classifier: Programming Language :: Python :: 3.7
Classifier: Programming Language :: Python :: 3.8
Classifier: Programming Language :: Python :: 3.9
Requires-Dist: ipywidgets (>=7.6.0)
Requires-Dist: jupyterlab (>=3)
Requires-Dist: thomas-core
